binance_archiver/__init__.py
binance_archiver/abstract_base_classes.py
binance_archiver/b2_client.py
binance_archiver/blackout_supervisor.py
binance_archiver/command_line_interface.py
binance_archiver/data_quality_checker.py
binance_archiver/data_quality_report.py
binance_archiver/data_sink_config.py
binance_archiver/data_sink_facade.py
binance_archiver/difference_depth_queue.py
binance_archiver/exceptions.py
binance_archiver/fastapi_manager.py
binance_archiver/individual_column_checker.py
binance_archiver/listener_facade.py
binance_archiver/listener_observer_updater.py
binance_archiver/load_config.py
binance_archiver/logo.py
binance_archiver/main_data_quality_analytics.py
binance_archiver/main_data_sink.py
binance_archiver/main_data_sink_with_vault.py
binance_archiver/main_listener.py
binance_archiver/main_scraper.py
binance_archiver/queue_pool.py
binance_archiver/s3_client.py
binance_archiver/scraper.py
binance_archiver/setup_logger.py
binance_archiver/snapshot_manager.py
binance_archiver/spinning_donut.py
binance_archiver/stream_data_saver_and_sender.py
binance_archiver/stream_listener.py
binance_archiver/stream_listener_id.py
binance_archiver/stream_service.py
binance_archiver/timestamps_generator.py
binance_archiver/trade_queue.py
binance_archiver/url_factory.py
binance_archiver/enum_/__init__.py
binance_archiver/enum_/asset_parameters.py
binance_archiver/enum_/commands_registry_enum.py
binance_archiver/enum_/data_quality_report_status_enum.py
binance_archiver/enum_/data_save_target_enum.py
binance_archiver/enum_/epoch_time_unit.py
binance_archiver/enum_/instruments_matrix.py
binance_archiver/enum_/interval_settings.py
binance_archiver/enum_/market_enum.py
binance_archiver/enum_/storage_connection_parameters.py
binance_archiver/enum_/stream_type_enum.py
binance_archiver/test/__init__.py
binance_archiver/test/test_binance_archiver_facade.py
binance_archiver/test/test_blackout_supervisor.py
binance_archiver/test/test_data_quality_checker.py
binance_archiver-0.0.3.dist-info/METADATA
binance_archiver-0.0.3.dist-info/WHEEL
binance_archiver-0.0.3.dist-info/top_level.txt
binance_archiver-0.0.3.dist-info/RECORD
